PaintPrint.py
paintprint-1.0.6.dist-info/WHEEL
paintprint-1.0.6.dist-info/METADATA
paintprint-1.0.6.dist-info/RECORD
