Metadata-Version: 2.1
Name: paintprint
Version: 1.0.6
Summary: This module can colorize any text in your terminal
Home-page: https://github.com/tankalxat34/PaintPrint
Author: tankalxat34
Author-email: tankalxat34@gmail.com
Requires-Python: >=3.6,<4.0
Classifier: Programming Language :: Python :: 3
Classifier: Programming Language :: Python :: 3.6
Classifier: Programming Language :: Python :: 3.7
Classifier: Programming Language :: Python :: 3.8
Classifier: Programming Language :: Python :: 3.9
Project-URL: Repository, https://github.com/tankalxat34/PaintPrint
